{
	"format_version": "1.8.0",
	"animations": {
		"animation.gauntlet.passive": {
			"loop": true,
			"animation_length": 4,
			"sound_effects": {
				"0.0": {
					"effect": "aviator_idle"
				}
			},
			"bones": {
				"root": {
					"position": {
						"0.0": {
							"vector": [0, 0, 0],
							"easing": "bezier",
							"left": [0, 0, 0],
							"left_time": [-0.1, -0.1, -0.1],
							"right": [0, 0, 0],
							"right_time": [0.1, 0.1, 0.1]
						},
						"0.0333": [0, 0.00079, 0],
						"0.4667": [0, 0.02315, 0],
						"0.9": [0, 0.04638, 0],
						"1.0": {
							"vector": [0, 0.05, 0],
							"easing": "bezier",
							"left": [0, 0, 0],
							"left_time": [-0.1, -0.1, -0.1],
							"right": [0, 0, 0],
							"right_time": [0.1, 0.1, 0.1]
						},
						"1.0333": [0, 0.04921, 0],
						"1.4667": [0, 0.02685, 0],
						"1.9": [0, 0.00362, 0],
						"2.0": {
							"vector": [0, 0, 0],
							"easing": "bezier",
							"left": [0, 0, 0],
							"left_time": [-0.1, -0.1, -0.1],
							"right": [0, 0, 0],
							"right_time": [0.1, 0.1, 0.1]
						},
						"2.0333": [0, -0.00079, 0],
						"2.4667": [0, -0.02315, 0],
						"2.9": [0, -0.04638, 0],
						"3.0": {
							"vector": [0, -0.05, 0],
							"easing": "bezier",
							"left": [0, 0, 0],
							"left_time": [-0.1, -0.1, -0.1],
							"right": [0, 0, 0],
							"right_time": [0.1, 0.1, 0.1]
						},
						"3.0333": [0, -0.04921, 0],
						"3.4667": [0, -0.02685, 0],
						"3.9": [0, -0.00362, 0],
						"4.0": {
							"vector": [0, 0, 0]
						}
					}
				},
				"needle": {
					"rotation": {
						"0.0": {
							"vector": [0, 0, 0]
						},
						"0.0333": {
							"vector": [-3.5, 0, 0]
						},
						"0.0667": {
							"vector": [0, 0, 0]
						},
						"0.1": {
							"vector": [0, 0, 0]
						},
						"0.1333": {
							"vector": [-3.5, 0, 0]
						},
						"0.1667": {
							"vector": [0, 0, 0]
						},
						"0.2": {
							"vector": [0, 0, 0]
						},
						"0.2333": {
							"vector": [-3.5, 0, 0]
						},
						"0.2667": {
							"vector": [0, 0, 0]
						},
						"0.3": {
							"vector": [0, 0, 0]
						},
						"0.3333": {
							"vector": [-3.5, 0, 0]
						},
						"0.3667": {
							"vector": [0, 0, 0]
						},
						"0.4": {
							"vector": [0, 0, 0]
						},
						"0.4333": {
							"vector": [-3.5, 0, 0]
						},
						"0.4667": {
							"vector": [0, 0, 0]
						},
						"0.5": {
							"vector": [0, 0, 0]
						},
						"0.5333": {
							"vector": [-3.5, 0, 0]
						},
						"0.5667": {
							"vector": [0, 0, 0]
						},
						"0.6": {
							"vector": [0, 0, 0]
						},
						"0.6333": {
							"vector": [-3.5, 0, 0]
						},
						"0.6667": {
							"vector": [0, 0, 0]
						},
						"0.7": {
							"vector": [0, 0, 0]
						},
						"0.7333": {
							"vector": [-3.5, 0, 0]
						},
						"0.7667": {
							"vector": [0, 0, 0]
						},
						"0.8": {
							"vector": [0, 0, 0]
						},
						"0.8333": {
							"vector": [-3.5, 0, 0]
						},
						"0.8667": {
							"vector": [0, 0, 0]
						},
						"0.9": {
							"vector": [0, 0, 0]
						},
						"0.9333": {
							"vector": [-3.5, 0, 0]
						},
						"0.9667": {
							"vector": [0, 0, 0]
						},
						"1.0": {
							"vector": [0, 0, 0]
						},
						"1.0333": {
							"vector": [-3.5, 0, 0]
						},
						"1.0667": {
							"vector": [0, 0, 0]
						},
						"1.1": {
							"vector": [0, 0, 0]
						},
						"1.1333": {
							"vector": [-3.5, 0, 0]
						},
						"1.1667": {
							"vector": [0, 0, 0]
						},
						"1.2": {
							"vector": [0, 0, 0]
						},
						"1.2333": {
							"vector": [-3.5, 0, 0]
						},
						"1.2667": {
							"vector": [0, 0, 0]
						},
						"1.3": {
							"vector": [0, 0, 0]
						},
						"1.3333": {
							"vector": [-3.5, 0, 0]
						},
						"1.3667": {
							"vector": [0, 0, 0]
						},
						"1.4": {
							"vector": [0, 0, 0]
						},
						"1.4333": {
							"vector": [-3.5, 0, 0]
						},
						"1.4667": {
							"vector": [0, 0, 0]
						},
						"1.5": {
							"vector": [0, 0, 0]
						},
						"1.5333": {
							"vector": [-3.5, 0, 0]
						},
						"1.5667": {
							"vector": [0, 0, 0]
						},
						"1.6": {
							"vector": [0, 0, 0]
						},
						"1.6333": {
							"vector": [-3.5, 0, 0]
						},
						"1.6667": {
							"vector": [0, 0, 0]
						},
						"1.7": {
							"vector": [0, 0, 0]
						},
						"1.7333": {
							"vector": [-3.5, 0, 0]
						},
						"1.7667": {
							"vector": [0, 0, 0]
						},
						"1.8": {
							"vector": [0, 0, 0]
						},
						"1.8333": {
							"vector": [-3.5, 0, 0]
						},
						"1.8667": {
							"vector": [0, 0, 0]
						},
						"1.9": {
							"vector": [0, 0, 0]
						},
						"1.9333": {
							"vector": [-3.5, 0, 0]
						},
						"1.9667": {
							"vector": [0, 0, 0]
						},
						"2.0": {
							"vector": [0, 0, 0]
						},
						"2.0333": {
							"vector": [-3.5, 0, 0]
						},
						"2.0667": {
							"vector": [0, 0, 0]
						},
						"2.1": {
							"vector": [0, 0, 0]
						},
						"2.1333": {
							"vector": [-3.5, 0, 0]
						},
						"2.1667": {
							"vector": [0, 0, 0]
						},
						"2.2": {
							"vector": [0, 0, 0]
						},
						"2.2333": {
							"vector": [-3.5, 0, 0]
						},
						"2.2667": {
							"vector": [0, 0, 0]
						},
						"2.3": {
							"vector": [0, 0, 0]
						},
						"2.3333": {
							"vector": [-3.5, 0, 0]
						},
						"2.3667": {
							"vector": [0, 0, 0]
						},
						"2.4": {
							"vector": [0, 0, 0]
						},
						"2.4333": {
							"vector": [-3.5, 0, 0]
						},
						"2.4667": {
							"vector": [0, 0, 0]
						},
						"2.5": {
							"vector": [0, 0, 0]
						},
						"2.5333": {
							"vector": [-3.5, 0, 0]
						},
						"2.5667": {
							"vector": [0, 0, 0]
						},
						"2.6": {
							"vector": [0, 0, 0]
						},
						"2.6333": {
							"vector": [-3.5, 0, 0]
						},
						"2.6667": {
							"vector": [0, 0, 0]
						},
						"2.7": {
							"vector": [0, 0, 0]
						},
						"2.7333": {
							"vector": [-3.5, 0, 0]
						},
						"2.7667": {
							"vector": [0, 0, 0]
						},
						"2.8": {
							"vector": [0, 0, 0]
						},
						"2.8333": {
							"vector": [-3.5, 0, 0]
						},
						"2.8667": {
							"vector": [0, 0, 0]
						},
						"2.9": {
							"vector": [0, 0, 0]
						},
						"2.9333": {
							"vector": [-3.5, 0, 0]
						},
						"2.9667": {
							"vector": [0, 0, 0]
						},
						"3.0": {
							"vector": [0, 0, 0]
						},
						"3.0333": {
							"vector": [-3.5, 0, 0]
						},
						"3.0667": {
							"vector": [0, 0, 0]
						},
						"3.1": {
							"vector": [0, 0, 0]
						},
						"3.1333": {
							"vector": [-3.5, 0, 0]
						},
						"3.1667": {
							"vector": [0, 0, 0]
						},
						"3.2": {
							"vector": [0, 0, 0]
						},
						"3.2333": {
							"vector": [-3.5, 0, 0]
						},
						"3.2667": {
							"vector": [0, 0, 0]
						},
						"3.3": {
							"vector": [-3.5, 0, 0]
						},
						"3.3333": {
							"vector": [0, 0, 0]
						},
						"3.3667": {
							"vector": [0, 0, 0]
						},
						"3.4": {
							"vector": [-3.5, 0, 0]
						},
						"3.4333": {
							"vector": [0, 0, 0]
						},
						"3.4667": {
							"vector": [-3.5, 0, 0]
						},
						"3.5": {
							"vector": [0, 0, 0]
						},
						"3.5333": {
							"vector": [0, 0, 0]
						},
						"3.5667": {
							"vector": [-3.5, 0, 0]
						},
						"3.6": {
							"vector": [0, 0, 0]
						},
						"3.6333": {
							"vector": [-3.5, 0, 0]
						},
						"3.6667": {
							"vector": [0, 0, 0]
						},
						"3.7": {
							"vector": [0, 0, 0]
						},
						"3.7333": {
							"vector": [-3.5, 0, 0]
						},
						"3.7667": {
							"vector": [0, 0, 0]
						},
						"3.8": {
							"vector": [-3.5, 0, 0]
						},
						"3.8333": {
							"vector": [0, 0, 0]
						},
						"3.8667": {
							"vector": [0, 0, 0]
						},
						"3.9": {
							"vector": [-3.5, 0, 0]
						},
						"3.9333": {
							"vector": [0, 0, 0]
						},
						"3.9667": {
							"vector": [-3.5, 0, 0]
						},
						"4.0": {
							"vector": [0, 0, 0]
						}
					}
				},
				"cogwheel_1": {
					"rotation": {
						"0.0": {
							"vector": [0, 0, 0]
						},
						"1.0": {
							"vector": [-180, 0, 0]
						},
						"2.0": {
							"vector": [-360, 0, 0]
						},
						"3.0": {
							"vector": [-540, 0, 0]
						},
						"4.0": {
							"vector": [-720, 0, 0]
						}
					}
				},
				"cogwheel_2": {
					"rotation": {
						"0.0": {
							"vector": [0, 0, 0]
						},
						"1.0": {
							"vector": [-360, 0, 0]
						},
						"2.0": {
							"vector": [-720, 0, 0]
						},
						"3.0": {
							"vector": [-1077.5, 0, 0]
						},
						"3.2333": {
							"vector": [-1147.5, 0, 0]
						},
						"3.5": {
							"vector": [-1197.5, 0, 0]
						},
						"3.7333": {
							"vector": [-1117.5, 0, 0]
						},
						"4.0": {
							"vector": [-1077.5, 0, 0]
						}
					}
				},
				"vent_passive_pipe": {
					"position": {
						"0.0": {

							"vector": [0, 0, 0]
						},
						"0.4": {
							"vector": [0, 0.01, -0.02]
						},
						"0.8": {
							"vector": [0, 0, 0]
						},
						"1.2": {
							"vector": [0, 0.01, -0.02]
						},
						"1.6": {
							"vector": [0, 0, 0]
						},
						"2.0": {
							"vector": [0, 0.01, -0.02]
						},
						"2.4": {
							"vector": [0, 0, 0]
						},
						"2.8": {
							"vector": [0, 0.01, -0.02]
						},
						"3.2": {
							"vector": [0, 0, 0]
						},
						"3.6": {
							"vector": [0, 0.01, -0.02]
						},
						"4.0": {
							"vector": [0, 0, 0]
						}
					}
				},
				"big_complex_cogwheel": {
					"rotation": {
						"0.0": {
							"vector": [0, 0, 0]
						},
						"1.0": {
							"vector": [90, 0, 0]
						},
						"1.5": {
							"vector": [138.47, 0, 0]
						},
						"2.0": {
							"vector": [180, 0, 0]
						},
						"3.0": {
							"vector": [270, 0, 0]
						},
						"4.0": {
							"vector": [360, 0, 0]
						}
					}
				},
				"big_complex_cogwheel_2": {
					"rotation": {
						"0.0": {
							"vector": [0, 0, 0]
						},
						"1.0": {
							"vector": [-90, 0, 0]
						},
						"2.0": {
							"vector": [-180, 0, 0]
						},
						"3.0": {
							"vector": [-270, 0, 0]
						},
						"4.0": {
							"vector": [-360, 0, 0]
						}
					}
				},
				"pusher_complex_cogwheel": {
					"rotation": {
						"0.0": {
							"vector": [0, 0, 0]
						},
						"1.0": {
							"vector": [-360, 0, 0]
						},
						"2.0": {
							"vector": [-720, 0, 0]
						},
						"3.0": {
							"vector": [-1080, 0, 0]
						},
						"4.0": {
							"vector": [-1440, 0, 0]
						}
					}
				}
			}
		},
		"animation.gauntlet.fire": {
			"animation_length": 1,
			"override_previous_animation": true,
			"bones": {
				"root": {
					"rotation": {
						"0.0": {
							"vector": [0, 0, 0]
						},
						"0.1333": {
							"vector": [0, 0, 0]
						}
					},
					"position": {
						"0.0": {
							"vector": [0, 0, 0]
						},
						"0.1333": {
							"vector": [0, 0, -0.12]
						},
						"1.0": {
							"vector": [0, 0, 0]
						}
					}
				},
				"needle": {
					"rotation": {
						"0.0": {
							"vector": [0, 0, 0]
						},
						"0.2667": {
							"vector": [-20, 0, 0]
						},
						"0.7667": {
							"vector": [0, 0, 0]
						}
					}
				},
				"push": {
					"position": {
						"0.0": {
							"vector": [0, 0, 0]
						},
						"0.0333": {
							"vector": [0, -0.925, 0]
						},
						"0.0667": {
							"vector": [0, -1.725, 0]
						},
						"0.1333": {
							"vector": [0, -3, 0]
						},
						"0.1667": {
							"vector": [0, -3, 0]
						},
						"0.2667": {
							"vector": [0, -1.725, 0]
						},
						"0.4": {
							"vector": [0, -0.925, 0]
						},
						"0.6333": {
							"vector": [0, 0, 0]
						}
					}
				},
				"cogwheel_1": {
					"rotation": {
						"0.1": {
							"vector": [0, 0, 0]
						},
						"0.2667": {
							"vector": [-360, 0, 0]
						},
						"1.0": {
							"vector": [-540, 0, 0]
						}
					}
				},
				"cogwheel_2": {
					"rotation": {
						"0.0": {
							"vector": [0, 0, 0]
						},
						"0.2667": {
							"vector": [-360, 0, 0]
						},
						"1.0": {
							"vector": [0, 0, 0]
						}
					}
				},
				"big_complex_cogwheel": {
					"rotation": {
						"0.0": {
							"vector": [0, 0, 0]
						},
						"1.0": {
							"vector": [360, 0, 0]
						}
					}
				},
				"big_complex_cogwheel_2": {
					"rotation": {
						"0.0": {
							"vector": [0, 0, 0]
						},
						"0.2667": {
							"vector": [-240, 0, 0]
						},
						"1.0": {
							"vector": [-360, 0, 0]
						}
					}
				},
				"pusher_complex_cogwheel": {
					"rotation": {
						"0.0": {
							"vector": [0, 0, 0]
						},
						"0.2667": {
							"vector": [360, 0, 0]
						},
						"1.0": {
							"vector": [595, 0, 0]
						}
					}
				},
				"rotation_fix": {
					"rotation": {
						"0.0": {
							"vector": [0, 0, 0]
						},
						"0.1333": {
							"vector": [0, 0, -12]
						},
						"0.2333": {
							"vector": [-2, 0, -12]
						},
						"0.2667": [-1.90402, 0, -11.42415],
						"0.3": [-1.45404, 0, -8.72424],
						"0.3333": [-0.54604, 0, -3.27621],
						"0.3667": [-0.096, 0, -0.57598],
						"0.4": {
							"vector": [0, 0, 0]
						}
					},
					"position": {
						"0.0": {
							"vector": [0, 0, 0]
						},
						"0.1333": {
							"vector": [0, 0.4, -0.03]
						},
						"0.2333": {
							"vector": [0, -0.1, -0.05]
						},
						"0.2667": [0, -0.0976, -0.0476],
						"0.3": [0, -0.08635, -0.03635],
						"0.3333": [0, -0.06365, -0.01365],
						"0.4": {
							"vector": [0, -0.05, 0]
						},
						"0.4333": [0, -0.04781, 0],
						"0.8667": [0, 0.0127, 0],
						"1.0": {
							"vector": [0, 0, 0]
						}
					}
				}
			}
		},
		"animation.gauntlet.tpv_fire": {
			"animation_length": 1,
			"override_previous_animation": true,
			"bones": {
				"root": {
					"position": {
						"0.0": {
							"vector": [0, 0, 0]
						},
						"0.1333": {
							"vector": [0, 0.55, 0]
						},
						"0.2333": {
							"vector": [0, -0.15, 0]
						},
						"0.2667": [0, -0.1452, 0],
						"0.3": [0, -0.1227, 0],
						"0.3333": [0, -0.0773, 0],
						"0.3667": [0, -0.0548, 0],
						"0.4": {
							"vector": [0, -0.05, 0]
						},
						"0.4333": [0, -0.04781, 0],
						"0.8667": [0, 0.0127, 0],
						"1.0": {
							"vector": [0, 0, 0]
						}
					}
				},
				"needle": {
					"rotation": {
						"0.0": {
							"vector": [0, 0, 0]
						},
						"0.2667": {
							"vector": [-20, 0, 0]
						},
						"0.7333": {
							"vector": [0, 0, 0]
						}
					}
				},
				"push": {
					"position": {
						"0.0": {
							"vector": [0, 0, 0]
						},
						"0.0333": {
							"vector": [0, -0.925, 0]
						},
						"0.0667": {
							"vector": [0, -1.725, 0]
						},
						"0.1333": {
							"vector": [0, -3, 0]
						},
						"0.1667": {
							"vector": [0, -3, 0]
						},
						"0.2667": {
							"vector": [0, -1.725, 0]
						},
						"0.4": {
							"vector": [0, -0.925, 0]
						},
						"0.6333": {
							"vector": [0, 0, 0]
						}
					}
				},
				"cogwheel_1": {
					"rotation": {
						"0.1": {
							"vector": [0, 0, 0]
						},
						"0.2667": {
							"vector": [-360, 0, 0]
						},
						"1.0": {
							"vector": [-540, 0, 0]
						}
					}
				},
				"cogwheel_2": {
					"rotation": {
						"0.0": {
							"vector": [0, 0, 0]
						},
						"0.2667": {
							"vector": [-360, 0, 0]
						},
						"1.0": {
							"vector": [0, 0, 0]
						}
					}
				},
				"big_complex_cogwheel": {
					"rotation": {
						"0.0": {
							"vector": [0, 0, 0]
						},
						"1.0": {
							"vector": [360, 0, 0]
						}
					}
				},
				"big_complex_cogwheel_2": {
					"rotation": {
						"0.0": {
							"vector": [0, 0, 0]
						},
						"0.2667": {
							"vector": [-240, 0, 0]
						},
						"1.0": {
							"vector": [-360, 0, 0]
						}
					}
				},
				"pusher_complex_cogwheel": {
					"rotation": {
						"0.0": {
							"vector": [0, 0, 0]
						},
						"0.2667": {
							"vector": [360, 0, 0]
						},
						"1.0": {
							"vector": [595, 0, 0]
						}
					}
				}
			}
		},
		"animation.gauntlet.cooldown": {
			"animation_length": 6.0333,
			"override_previous_animation": true,
			"bones": {
				"root": {
					"position": {
						"0.0333": {
							"vector": [0, 0, 0]
						},
						"0.0667": {
							"vector": [-0.05, 0, 0]
						},
						"0.1": {
							"vector": [0, 0, 0]
						},
						"0.1333": {
							"vector": [0.05, -0.2, 0]
						},
						"0.1667": {
							"vector": [0, 0, 0]
						},
						"0.2": {
							"vector": [0, -0.3, 0]
						},
						"0.2333": {
							"vector": [0, -0.4, 0]
						},
						"0.2667": {
							"vector": [0, -0.3, 0]
						},
						"0.3": {
							"vector": [0, -0.2, 0]
						},
						"0.3333": {
							"vector": [0, -0.1, 0]
						},
						"0.3667": {
							"vector": [0, 0, 0]
						},
						"0.4": [0, 0.00057, 0],
						"0.8333": [0, 0.01425, 0],
						"1.2667": [0, 0.02898, 0],
						"1.7": [0, 0.04347, 0],
						"1.9333": {
							"vector": [0, 0.05, 0]
						},
						"1.9667": {
							"vector": [0, 0.1, 0]
						},
						"2.0": {
							"vector": [0, 0.2, 0]
						},
						"2.0333": {
							"vector": [0, -0.1, 0]
						},
						"2.0667": [0, -0.10433, 0],
						"2.1": [0, -0.12037, 0],
						"2.1667": [0, -0.17963, 0],
						"2.2": [0, -0.19567, 0],
						"2.2333": {
							"vector": [0, -0.2, 0]
						},
						"2.2667": {
							"vector": [0.1, 0, 0]
						},
						"2.3": {
							"vector": [0, 0, 0]
						},
						"2.3333": {
							"vector": [-0.1, 0, 0]
						},
						"2.3667": {
							"vector": [0, 0, 0]
						},
						"2.4": {
							"vector": [0, 0, 0]
						},
						"3.7": {
							"vector": [0, -0.1, 0]
						},
						"3.7333": {
							"vector": [0, 0, 0]
						},
						"3.7667": [-0.00131, 0.00262, 0.00131],
						"4.2": [-0.03476, 0.06952, 0.03476],
						"4.6333": [-0.07074, 0.14148, 0.07074],
						"5.0333": {
							"vector": [-0.1, 0.2, 0.1]
						},
						"5.0667": {
							"vector": [0, 0.05, 0]
						},
						"5.1": {
							"vector": [0.1, -0.1, 0]
						},
						"5.1333": {
							"vector": [0, 0, 0]
						}
					}
				},
				"needle": {
					"rotation": {
						"0.0": {
							"vector": [0, 0, 0]
						},
						"0.0667": {
							"vector": [-42.5, 0, 0]
						},
						"0.1333": {
							"vector": [-33.5, 0, 0]
						},
						"0.1667": {
							"vector": [-42.5, 0, 0]
						},
						"0.2333": {
							"vector": [-33.5, 0, 0]
						},
						"0.2667": {
							"vector": [-42.5, 0, 0]
						},
						"0.3333": {
							"vector": [-33.5, 0, 0]
						},
						"0.3667": {
							"vector": [-42.5, 0, 0]
						},
						"0.4333": {
							"vector": [-33.5, 0, 0]
						},
						"0.4667": {
							"vector": [-42.5, 0, 0]
						},
						"0.5333": {
							"vector": [-33.5, 0, 0]
						},
						"0.5667": {
							"vector": [-42.5, 0, 0]
						},
						"0.6": {
							"vector": [-33.5, 0, 0]
						},
						"0.6333": {
							"vector": [-42.5, 0, 0]
						},
						"0.7": {
							"vector": [-33.5, 0, 0]
						},
						"0.7333": {
							"vector": [-33.5, 0, 0]
						},
						"0.7667": {
							"vector": [-42.5, 0, 0]
						},
						"0.8": {
							"vector": [-33.5, 0, 0]
						},
						"0.8333": {
							"vector": [-42.5, 0, 0]
						},
						"0.8667": {
							"vector": [-33.5, 0, 0]
						},
						"0.9": {
							"vector": [-42.5, 0, 0]
						},
						"0.9667": {
							"vector": [-33.5, 0, 0]
						},
						"1.0": {
							"vector": [-42.5, 0, 0]
						},
						"1.0667": {
							"vector": [-33.5, 0, 0]
						},
						"1.1": {
							"vector": [-42.5, 0, 0]
						},
						"1.1667": {
							"vector": [-33.5, 0, 0]
						},
						"1.2": {
							"vector": [-42.5, 0, 0]
						},
						"1.2667": {
							"vector": [-33.5, 0, 0]
						},
						"1.3": {
							"vector": [-42.5, 0, 0]
						},
						"1.3333": {
							"vector": [-33.5, 0, 0]
						},
						"1.3667": {
							"vector": [-42.5, 0, 0]
						},
						"1.4333": {
							"vector": [-33.5, 0, 0]
						},
						"1.4667": {
							"vector": [-33.5, 0, 0]
						},
						"1.5": {
							"vector": [-42.5, 0, 0]
						},
						"1.5333": {
							"vector": [-33.5, 0, 0]
						},
						"1.5667": {
							"vector": [-42.5, 0, 0]
						},
						"1.6333": {
							"vector": [-33.5, 0, 0]
						},
						"1.6667": {
							"vector": [-42.5, 0, 0]
						},
						"1.7333": {
							"vector": [-33.5, 0, 0]
						},
						"1.7667": {
							"vector": [-42.5, 0, 0]
						},
						"1.8333": {
							"vector": [-33.5, 0, 0]
						},
						"1.8667": {
							"vector": [-42.5, 0, 0]
						},
						"1.9333": {
							"vector": [-33.5, 0, 0]
						},
						"1.9667": {
							"vector": [-42.5, 0, 0]
						},
						"2.0333": {
							"vector": [-33.5, 0, 0]
						},
						"2.0667": {
							"vector": [-42.5, 0, 0]
						},
						"2.1": {
							"vector": [-33.5, 0, 0]
						},
						"2.1333": {
							"vector": [-42.5, 0, 0]
						},
						"2.2": {
							"vector": [-33.5, 0, 0]
						},
						"2.2333": {
							"vector": [-33.5, 0, 0]
						},
						"2.2667": {
							"vector": [-42.5, 0, 0]
						},
						"2.3": {
							"vector": [-33.5, 0, 0]
						},
						"2.3333": {
							"vector": [-42.5, 0, 0]
						},
						"2.3667": {
							"vector": [-33.5, 0, 0]
						},
						"2.4": {
							"vector": [-42.5, 0, 0]
						},
						"2.4667": {
							"vector": [-33.5, 0, 0]
						},
						"2.5": {
							"vector": [-42.5, 0, 0]
						},
						"2.5667": {
							"vector": [-33.5, 0, 0]
						},
						"2.6": {
							"vector": [-42.5, 0, 0]
						},
						"2.6667": {
							"vector": [-33.5, 0, 0]
						},
						"2.7": {
							"vector": [-42.5, 0, 0]
						},
						"2.7667": {
							"vector": [-33.5, 0, 0]
						},
						"2.8": {
							"vector": [-42.5, 0, 0]
						},
						"2.8333": {
							"vector": [-33.5, 0, 0]
						},
						"2.8667": {
							"vector": [-42.5, 0, 0]
						},
						"2.9333": {
							"vector": [-33.5, 0, 0]
						},
						"2.9667": {
							"vector": [-33.5, 0, 0]
						},
						"3.0": {
							"vector": [-42.5, 0, 0]
						},
						"3.0333": {
							"vector": [-33.5, 0, 0]
						},
						"3.0667": {
							"vector": [-42.5, 0, 0]
						},
						"3.1333": {
							"vector": [-33.5, 0, 0]
						},
						"3.1667": {
							"vector": [-42.5, 0, 0]
						},
						"3.2333": {
							"vector": [-33.5, 0, 0]
						},
						"3.2667": {
							"vector": [-42.5, 0, 0]
						},
						"3.3333": {
							"vector": [-33.5, 0, 0]
						},
						"3.3667": {
							"vector": [-42.5, 0, 0]
						},
						"3.4333": {
							"vector": [-33.5, 0, 0]
						},
						"3.4667": {
							"vector": [-42.5, 0, 0]
						},
						"3.5333": {
							"vector": [-33.5, 0, 0]
						},
						"3.5667": {
							"vector": [-42.5, 0, 0]
						},
						"3.6": {
							"vector": [-33.5, 0, 0]
						},
						"3.6333": {
							"vector": [-42.5, 0, 0]
						},
						"3.7": {
							"vector": [-33.5, 0, 0]
						},
						"3.7333": {
							"vector": [-33.5, 0, 0]
						},
						"3.7667": {
							"vector": [-42.5, 0, 0]
						},
						"3.8": {
							"vector": [-33.5, 0, 0]
						},
						"3.8333": {
							"vector": [-42.5, 0, 0]
						},
						"3.8667": {
							"vector": [-33.5, 0, 0]
						},
						"3.9": {
							"vector": [-42.5, 0, 0]
						},
						"3.9667": {
							"vector": [-33.5, 0, 0]
						},
						"4.0": {
							"vector": [-42.5, 0, 0]
						},
						"4.0667": {
							"vector": [-33.5, 0, 0]
						},
						"4.1": {
							"vector": [-42.5, 0, 0]
						},
						"4.1667": {
							"vector": [-33.5, 0, 0]
						},
						"4.2": {
							"vector": [-42.5, 0, 0]
						},
						"4.2667": {
							"vector": [-33.5, 0, 0]
						},
						"4.3": {
							"vector": [-42.5, 0, 0]
						},
						"4.3333": {
							"vector": [-33.5, 0, 0]
						},
						"4.3667": {
							"vector": [-42.5, 0, 0]
						},
						"4.4333": {
							"vector": [-33.5, 0, 0]
						},
						"4.4667": {
							"vector": [-33.5, 0, 0]
						},
						"4.5": {
							"vector": [-42.5, 0, 0]
						},
						"4.5333": {
							"vector": [-33.5, 0, 0]
						},
						"4.5667": {
							"vector": [-42.5, 0, 0]
						},
						"4.6333": {
							"vector": [-33.5, 0, 0]
						},
						"4.6667": {
							"vector": [-42.5, 0, 0]
						},
						"4.7333": {
							"vector": [-33.5, 0, 0]
						},
						"4.7667": {
							"vector": [-42.5, 0, 0]
						},
						"4.8333": {
							"vector": [-33.5, 0, 0]
						},
						"4.8667": {
							"vector": [-42.5, 0, 0]
						},
						"4.9333": {
							"vector": [-33.5, 0, 0]
						},
						"4.9667": {
							"vector": [-42.5, 0, 0]
						},
						"5.0333": {
							"vector": [-33.5, 0, 0]
						},
						"5.0667": {
							"vector": [-42.5, 0, 0]
						},
						"5.1": {
							"vector": [-33.5, 0, 0]
						},
						"5.1333": {
							"vector": [-42.5, 0, 0]
						},
						"5.2": {
							"vector": [-33.5, 0, 0]
						},
						"5.2333": {
							"vector": [-33.5, 0, 0]
						},
						"5.2667": {
							"vector": [-42.5, 0, 0]
						},
						"5.3": {
							"vector": [-33.5, 0, 0]
						},
						"5.3333": {
							"vector": [-42.5, 0, 0]
						},
						"5.3667": {
							"vector": [-33.5, 0, 0]
						},
						"5.4": {
							"vector": [-30.5, 0, 0]
						},
						"5.4667": {
							"vector": [-28.5, 0, 0]
						},
						"5.5": {
							"vector": [-24.5, 0, 0]
						},
						"5.5667": {
							"vector": [-22.5, 0, 0]
						},
						"5.6": {
							"vector": [-19.5, 0, 0]
						},
						"5.6667": {
							"vector": [-15.5, 0, 0]
						},
						"5.7": {
							"vector": [-13.5, 0, 0]
						},
						"5.7667": {
							"vector": [-10.5, 0, 0]
						},
						"5.8": {
							"vector": [-9.5, 0, 0]
						},
						"5.8333": {
							"vector": [-6.5, 0, 0]
						},
						"5.8667": {
							"vector": [-3.5, 0, 0]
						},
						"6.0": {
							"vector": [0, 0, 0]
						}
					}
				},
				"push": {
					"position": {
						"0.0": {
							"vector": [0, 0, 0]
						},
						"0.0333": [0, 0, 0],
						"0.4667": [0, 0, 0],
						"0.9": [0, 0, 0],
						"1.3333": [0, 0, 0],
						"1.7667": [0, 0, 0],
						"2.2": [0, 0, 0],
						"2.5": {
							"vector": [0, 0, 0]
						},
						"2.5333": [0, -0.04768, 0],
						"2.5667": [0, -0.22402, 0],
						"2.6333": [0, -0.87598, 0],
						"2.6667": [0, -1.05232, 0],
						"2.7": {
							"vector": [0, -1.1, 0]
						},
						"3.0": {
							"vector": [0, -1.7, 0]
						},
						"3.3": {
							"vector": [0, -2.4, 0]
						},
						"3.6": {
							"vector": [0, -2.9, 0]
						},
						"3.7": {
							"vector": [0, -3.2, 0]
						},
						"3.7333": [0, -3.18971, 0],
						"3.7667": [0, -3.16214, 0],
						"3.9": [0, -2.97778, 0],
						"3.9333": [0, -2.93786, 0],
						"3.9667": [0, -2.91029, 0],
						"4.0": {
							"vector": [0, -2.9, 0]
						},
						"4.0333": [0, -2.9, 0],
						"4.4667": [0, -2.9, 0],
						"4.8": {
							"vector": [0, -2.9, 0]
						},
						"4.8333": [0, -2.83494, 0],
						"4.9": [0, -1.76504, 0],
						"4.9333": {
							"vector": [0, -1.7, 0]
						},
						"5.0": {
							"vector": [0, -0.9, 0]
						},
						"5.0333": {
							"vector": [0, 0, 0]
						}
					}
				},
				"cogwheel_1": {
					"rotation": {
						"0.0": {
							"vector": [0, 0, 0]
						},
						"0.4": {
							"vector": [-270, 0, 0]
						},
						"0.5": {
							"vector": [-360, 0, 0]
						},
						"0.8": {
							"vector": [-720, 0, 0]
						},
						"1.0": {
							"vector": [-1080, 0, 0]
						},
						"1.2": {
							"vector": [-1620, 0, 0]
						},
						"1.5": {
							"vector": [-1980, 0, 0]
						},
						"2.0": {
							"vector": [-2340, 0, 0]
						},
						"2.5": {
							"vector": [-2700, 0, 0]
						},
						"3.0": {
							"vector": [-3060, 0, 0]
						},
						"3.5": {
							"vector": [-3420, 0, 0]
						},
						"4.0": {
							"vector": [-3780, 0, 0]
						},
						"4.5": {
							"vector": [-4050, 0, 0]
						},
						"5.0": {
							"vector": [-4230, 0, 0]
						},
						"5.5": {
							"vector": [-4320, 0, 0]
						},
						"6.0": {
							"vector": [-4410, 0, 0]
						}
					}
				},
				"cogwheel_2": {
					"rotation": {
						"0.0": {
							"vector": [0, 0, 0]
						},
						"0.4": {
							"vector": [360, 0, 0]
						},
						"0.5": {
							"vector": [440, 0, 0]
						},
						"0.8": {
							"vector": [800, 0, 0]
						},
						"1.0": {
							"vector": [1340, 0, 0]
						},
						"1.2": {
							"vector": [1700, 0, 0]
						},
						"1.5": {
							"vector": [2060, 0, 0]
						},
						"2.0": {
							"vector": [2420, 0, 0]
						},
						"2.5": {
							"vector": [2960, 0, 0]
						},
						"3.0": {
							"vector": [3500, 0, 0]
						},
						"3.5": {
							"vector": [4040, 0, 0]
						},
						"4.0": {
							"vector": [4580, 0, 0]
						},
						"4.5": {
							"vector": [5030, 0, 0]
						},
						"5.0": {
							"vector": [5390, 0, 0]
						},
						"5.5": {
							"vector": [5660, 0, 0]
						},
						"6.0": {
							"vector": [5840, 0, 0]
						}
					}
				},
				"big_complex_cogwheel": {
					"rotation": {
						"0.0": {
							"vector": [0, 0, 0]
						},
						"0.0333": [15.60288, 0, 0],
						"0.0667": [73.31588, 0, 0],
						"0.1333": [286.68412, 0, 0],
						"0.1667": [344.39712, 0, 0],
						"0.2": {
							"vector": [360, 0, 0]
						},
						"0.2333": [375.60288, 0, 0],
						"0.2667": [433.31588, 0, 0],
						"0.3333": [646.68412, 0, 0],
						"0.3667": [704.39712, 0, 0],
						"0.4": {
							"vector": [720, 0, 0]
						},
						"0.4333": [735.60288, 0, 0],
						"0.4667": [793.31588, 0, 0],
						"0.5333": [1006.68412, 0, 0],
						"0.5667": [1064.39712, 0, 0],
						"0.6": {
							"vector": [1080, 0, 0]
						},
						"0.6333": [1085.18918, 0, 0],
						"0.6667": [1097.11375, 0, 0],
						"0.7": [1112.8252, 0, 0],
						"0.7333": [1130.80432, 0, 0],
						"0.7667": [1150.09843, 0, 0],
						"0.8333": [1189.90157, 0, 0],
						"0.8667": [1209.19568, 0, 0],
						"0.9": [1227.1748, 0, 0],
						"0.9333": [1242.88625, 0, 0],
						"0.9667": [1254.81082, 0, 0],
						"1.0": {
							"vector": [1260, 0, 0]
						},
						"1.0333": [1262.25542, 0, 0],
						"1.0667": [1266.9664, 0, 0],
						"1.1": [1272.8689, 0, 0],
						"1.1333": [1279.46746, 0, 0],
						"1.1667": [1286.50106, 0, 0],
						"1.2": [1293.80293, 0, 0],
						"1.3": [1316.19707, 0, 0],
						"1.3333": [1323.49894, 0, 0],
						"1.3667": [1330.53254, 0, 0],
						"1.4": [1337.1311, 0, 0],
						"1.4333": [1343.0336, 0, 0],
						"1.4667": [1347.74458, 0, 0],
						"1.5": {
							"vector": [1350, 0, 0]
						},
						"1.5333": [1347.74458, 0, 0],
						"1.5667": [1343.0336, 0, 0],
						"1.6": [1337.1311, 0, 0],
						"1.6333": [1330.53254, 0, 0],
						"1.6667": [1323.49894, 0, 0],
						"1.7": [1316.19707, 0, 0],
						"1.8": [1293.80293, 0, 0],
						"1.8333": [1286.50106, 0, 0],
						"1.8667": [1279.46746, 0, 0],
						"1.9": [1272.8689, 0, 0],
						"1.9333": [1266.9664, 0, 0],
						"1.9667": [1262.25542, 0, 0],
						"2.0": {
							"vector": [1260, 0, 0]
						},
						"2.0333": [1254.81082, 0, 0],
						"2.0667": [1242.88625, 0, 0],
						"2.1": [1227.1748, 0, 0],
						"2.1333": [1209.19568, 0, 0],
						"2.1667": [1189.90157, 0, 0],
						"2.2333": [1150.09843, 0, 0],
						"2.2667": [1130.80432, 0, 0],
						"2.3": [1112.8252, 0, 0],
						"2.3333": [1097.11375, 0, 0],
						"2.3667": [1085.18918, 0, 0],
						"2.4": {
							"vector": [1080, 0, 0]
						},
						"2.4333": [1064.39712, 0, 0],
						"2.4667": [1006.68412, 0, 0],
						"2.5333": [793.31588, 0, 0],
						"2.5667": [735.60288, 0, 0],
						"2.6": {
							"vector": [720, 0, 0]
						},
						"2.6333": [704.39712, 0, 0],
						"2.6667": [646.68412, 0, 0],
						"2.7333": [433.31588, 0, 0],
						"2.7667": [375.60288, 0, 0],
						"2.8": {
							"vector": [360, 0, 0]
						},
						"2.8333": [344.39712, 0, 0],
						"2.8667": [286.68412, 0, 0],
						"2.9333": [73.31588, 0, 0],
						"2.9667": [15.60288, 0, 0],
						"3.0": {
							"vector": [0, 0, 0]
						},
						"3.0333": [15.60288, 0, 0],
						"3.0667": [73.31588, 0, 0],
						"3.1333": [286.68412, 0, 0],
						"3.1667": [344.39712, 0, 0],
						"3.2": {
							"vector": [360, 0, 0]
						},
						"3.2333": [375.60288, 0, 0],
						"3.2667": [433.31588, 0, 0],
						"3.3333": [646.68412, 0, 0],
						"3.3667": [704.39712, 0, 0],
						"3.4": {
							"vector": [720, 0, 0]
						},
						"3.4333": [735.60288, 0, 0],
						"3.4667": [793.31588, 0, 0],
						"3.5333": [1006.68412, 0, 0],
						"3.5667": [1064.39712, 0, 0],
						"3.6": {
							"vector": [1080, 0, 0]
						},
						"3.6333": [1085.18918, 0, 0],
						"3.6667": [1097.11375, 0, 0],
						"3.7": [1112.8252, 0, 0],
						"3.7333": [1130.80432, 0, 0],
						"3.7667": [1150.09843, 0, 0],
						"3.8333": [1189.90157, 0, 0],
						"3.8667": [1209.19568, 0, 0],
						"3.9": [1227.1748, 0, 0],
						"3.9333": [1242.88625, 0, 0],
						"3.9667": [1254.81082, 0, 0],
						"4.0": {
							"vector": [1260, 0, 0]
						},
						"4.0333": [1262.25542, 0, 0],
						"4.0667": [1266.9664, 0, 0],
						"4.1": [1272.8689, 0, 0],
						"4.1333": [1279.46746, 0, 0],
						"4.1667": [1286.50106, 0, 0],
						"4.2": [1293.80293, 0, 0],
						"4.3": [1316.19707, 0, 0],
						"4.3333": [1323.49894, 0, 0],
						"4.3667": [1330.53254, 0, 0],
						"4.4": [1337.1311, 0, 0],
						"4.4333": [1343.0336, 0, 0],
						"4.4667": [1347.74458, 0, 0],
						"4.5": {
							"vector": [1350, 0, 0]
						},
						"4.5333": [1347.74458, 0, 0],
						"4.5667": [1343.0336, 0, 0],
						"4.6": [1337.1311, 0, 0],
						"4.6333": [1330.53254, 0, 0],
						"4.6667": [1323.49894, 0, 0],
						"4.7": [1316.19707, 0, 0],
						"4.8": [1293.80293, 0, 0],
						"4.8333": [1286.50106, 0, 0],
						"4.8667": [1279.46746, 0, 0],
						"4.9": [1272.8689, 0, 0],
						"4.9333": [1266.9664, 0, 0],
						"4.9667": [1262.25542, 0, 0],
						"5.0": {
							"vector": [1260, 0, 0]
						},
						"5.0333": [1254.81082, 0, 0],
						"5.0667": [1242.88625, 0, 0],
						"5.1": [1227.1748, 0, 0],
						"5.1333": [1209.19568, 0, 0],
						"5.1667": [1189.90157, 0, 0],
						"5.2333": [1150.09843, 0, 0],
						"5.2667": [1130.80432, 0, 0],
						"5.3": [1112.8252, 0, 0],
						"5.3333": [1097.11375, 0, 0],
						"5.3667": [1085.18918, 0, 0],
						"5.4": {
							"vector": [1080, 0, 0]
						},
						"5.4333": [1064.39712, 0, 0],
						"5.4667": [1006.68412, 0, 0],
						"5.5333": [793.31588, 0, 0],
						"5.5667": [735.60288, 0, 0],
						"5.6": {
							"vector": [720, 0, 0]
						},
						"5.6333": [704.39712, 0, 0],
						"5.6667": [646.68412, 0, 0],
						"5.7333": [433.31588, 0, 0],
						"5.7667": [375.60288, 0, 0],
						"5.8": {
							"vector": [360, 0, 0]
						},
						"5.8333": [344.39712, 0, 0],
						"5.8667": [286.68412, 0, 0],
						"5.9333": [73.31588, 0, 0],
						"5.9667": [15.60288, 0, 0],
						"6.0": {
							"vector": [0, 0, 0]
						}
					}
				},
				"big_complex_cogwheel_2": {
					"rotation": {
						"0.0": {
							"vector": [0, 0, 0]
						},
						"0.0333": [-10.37836, 0, 0],
						"0.0667": [-34.2275, 0, 0],
						"0.1": [-65.65041, 0, 0],
						"0.1333": [-101.60865, 0, 0],
						"0.1667": [-140.19687, 0, 0],
						"0.2333": [-219.80313, 0, 0],
						"0.2667": [-258.39135, 0, 0],
						"0.3": [-294.34959, 0, 0],
						"0.3333": [-325.7725, 0, 0],
						"0.3667": [-349.62164, 0, 0],
						"0.4": {
							"vector": [-360, 0, 0]
						},
						"0.4333": [-371.59818, 0, 0],
						"0.4667": [-400.82611, 0, 0],
						"0.5": [-441.50181, 0, 0],
						"0.5333": [-489.10944, 0, 0],
						"0.6": [-590.89553, 0, 0],
						"0.6333": [-638.50267, 0, 0],
						"0.6667": [-679.17745, 0, 0],
						"0.7": [-708.40398, 0, 0],
						"0.7333": {
							"vector": [-720, 0, 0]
						},
						"0.7667": [-733.23154, 0, 0],
						"0.8": [-771.52008, 0, 0],
						"0.8333": [-830.0195, 0, 0],
						"0.9": [-969.9739, 0, 0],
						"0.9333": [-1028.47497, 0, 0],
						"0.9667": [-1066.76579, 0, 0],
						"1.0": {
							"vector": [-1080, 0, 0]
						},
						"1.0333": [-1090.37836, 0, 0],
						"1.0667": [-1114.2275, 0, 0],
						"1.1": [-1145.65041, 0, 0],
						"1.1333": [-1181.60865, 0, 0],
						"1.1667": [-1220.19687, 0, 0],
						"1.2333": [-1299.80313, 0, 0],
						"1.2667": [-1338.39135, 0, 0],
						"1.3": [-1374.34959, 0, 0],
						"1.3333": [-1405.7725, 0, 0],
						"1.3667": [-1429.62164, 0, 0],
						"1.4": {
							"vector": [-1440, 0, 0]
						},
						"1.4333": [-1452.3493, 0, 0],
						"1.4667": [-1485.4358, 0, 0],
						"1.5": [-1533.33534, 0, 0],
						"1.5333": [-1590.12376, 0, 0],
						"1.5667": [-1649.87624, 0, 0],
						"1.6": [-1706.66466, 0, 0],
						"1.6333": [-1754.5642, 0, 0],
						"1.6667": [-1787.6507, 0, 0],
						"1.7": {
							"vector": [-1800, 0, 0]
						},
						"1.7333": [-1812.3493, 0, 0],
						"1.7667": [-1845.4358, 0, 0],
						"1.8": [-1893.33534, 0, 0],
						"1.8333": [-1950.12376, 0, 0],
						"1.8667": [-2009.87624, 0, 0],
						"1.9": [-2066.66466, 0, 0],
						"1.9333": [-2114.5642, 0, 0],
						"1.9667": [-2147.6507, 0, 0],
						"2.0": {
							"vector": [-2160, 0, 0]
						},
						"2.0333": [-2172.3493, 0, 0],
						"2.0667": [-2205.4358, 0, 0],
						"2.1": [-2253.33534, 0, 0],
						"2.1333": [-2310.12376, 0, 0],
						"2.1667": [-2369.87624, 0, 0],
						"2.2": [-2426.66466, 0, 0],
						"2.2333": [-2474.5642, 0, 0],
						"2.2667": [-2507.6507, 0, 0],
						"2.3": {
							"vector": [-2520, 0, 0]
						},
						"2.3333": [-2532.3493, 0, 0],
						"2.3667": [-2565.4358, 0, 0],
						"2.4": [-2613.33534, 0, 0],
						"2.4333": [-2670.12376, 0, 0],
						"2.4667": [-2729.87624, 0, 0],
						"2.5": [-2786.66466, 0, 0],
						"2.5333": [-2834.5642, 0, 0],
						"2.5667": [-2867.6507, 0, 0],
						"2.6": {
							"vector": [-2880, 0, 0]
						},
						"2.6333": [-2892.3493, 0, 0],
						"2.6667": [-2925.4358, 0, 0],
						"2.7": [-2973.33534, 0, 0],
						"2.7333": [-3030.12376, 0, 0],
						"2.7667": [-3089.87624, 0, 0],
						"2.8": [-3146.66466, 0, 0],
						"2.8333": [-3194.5642, 0, 0],
						"2.8667": [-3227.6507, 0, 0],
						"2.9": {
							"vector": [-3240, 0, 0]
						},
						"2.9333": [-3252.00626, 0, 0],
						"2.9667": [-3284.17369, 0, 0],
						"3.0": [-3330.74269, 0, 0],
						"3.0333": [-3385.95366, 0, 0],
						"3.0667": [-3444.04634, 0, 0],
						"3.1": [-3499.25731, 0, 0],
						"3.1333": [-3545.82631, 0, 0],
						"3.1667": [-3577.99374, 0, 0],
						"3.2": {
							"vector": [-3590, 0, 0]
						},
						"3.2333": [-3602.3493, 0, 0],
						"3.2667": [-3635.4358, 0, 0],
						"3.3": [-3683.33534, 0, 0],
						"3.3333": [-3740.12376, 0, 0],
						"3.3667": [-3799.87624, 0, 0],
						"3.4": [-3856.66466, 0, 0],
						"3.4333": [-3904.5642, 0, 0],
						"3.4667": [-3937.6507, 0, 0],
						"3.5": {
							"vector": [-3950, 0, 0]
						},
						"3.5333": [-3962.3493, 0, 0],
						"3.5667": [-3995.4358, 0, 0],
						"3.6": [-4043.33534, 0, 0],
						"3.6333": [-4100.12376, 0, 0],
						"3.6667": [-4159.87624, 0, 0],
						"3.7": [-4216.66466, 0, 0],
						"3.7333": [-4264.5642, 0, 0],
						"3.7667": [-4297.6507, 0, 0],
						"3.8": {
							"vector": [-4310, 0, 0]
						},
						"3.8333": [-4323.37841, 0, 0],
						"3.8667": [-4359.22212, 0, 0],
						"3.9": [-4411.11328, 0, 0],
						"3.9333": [-4472.63407, 0, 0],
						"3.9667": [-4537.36593, 0, 0],
						"4.0": [-4598.88671, 0, 0],
						"4.0333": [-4650.77788, 0, 0],
						"4.0667": [-4686.62159, 0, 0],
						"4.1": {
							"vector": [-4700, 0, 0]
						},
						"4.1333": [-4709.51349, 0, 0],
						"4.1667": [-4731.37521, 0, 0],
						"4.2": [-4760.17954, 0, 0],
						"4.2333": [-4793.14126, 0, 0],
						"4.2667": [-4828.5138, 0, 0],
						"4.3333": [-4901.4862, 0, 0],
						"4.3667": [-4936.85874, 0, 0],
						"4.4": [-4969.82046, 0, 0],
						"4.4333": [-4998.62479, 0, 0],
						"4.4667": [-5020.48651, 0, 0],
						"4.5": {
							"vector": [-5030, 0, 0]
						},
						"4.5333": [-5036.76626, 0, 0],
						"4.5667": [-5050.89919, 0, 0],
						"4.6": [-5068.6067, 0, 0],
						"4.6333": [-5088.40238, 0, 0],
						"4.6667": [-5109.50319, 0, 0],
						"4.7": [-5131.40878, 0, 0],
						"4.7333": [-5153.75593, 0, 0],
						"4.7667": [-5176.24407, 0, 0],
						"4.8": [-5198.59122, 0, 0],
						"4.8333": [-5220.49681, 0, 0],
						"4.8667": [-5241.59762, 0, 0],
						"4.9": [-5261.3933, 0, 0],
						"4.9333": [-5279.10081, 0, 0],
						"4.9667": [-5293.23374, 0, 0],
						"5.0": {
							"vector": [-5300, 0, 0]
						},
						"5.0333": [-5303.75903, 0, 0],
						"5.0667": [-5311.61066, 0, 0],
						"5.1": [-5321.44816, 0, 0],
						"5.1333": [-5332.44577, 0, 0],
						"5.1667": [-5344.16844, 0, 0],
						"5.2": [-5356.33821, 0, 0],
						"5.3": [-5393.66179, 0, 0],
						"5.3333": [-5405.83156, 0, 0],
						"5.3667": [-5417.55423, 0, 0],
						"5.4": [-5428.55184, 0, 0],
						"5.4333": [-5438.38934, 0, 0],
						"5.4667": [-5446.24097, 0, 0],
						"5.5": {
							"vector": [-5450, 0, 0]
						},
						"5.5333": [-5452.75662, 0, 0],
						"5.5667": [-5458.51448, 0, 0],
						"5.6": [-5465.72865, 0, 0],
						"5.6333": [-5473.79356, 0, 0],
						"5.6667": [-5482.39019, 0, 0],
						"5.7": [-5491.31469, 0, 0],
						"5.8": [-5518.68531, 0, 0],
						"5.8333": [-5527.60981, 0, 0],
						"5.8667": [-5536.20644, 0, 0],
						"5.9": [-5544.27135, 0, 0],
						"5.9333": [-5551.48552, 0, 0],
						"5.9667": [-5557.24338, 0, 0],
						"6.0": {
							"vector": [-5560, 0, 0]
						}
					}
				},
				"mini_complex_cogwheel_2": {
					"rotation": {
						"0.1": {
							"vector": [0, 0, 0]
						},
						"0.4": {
							"vector": [360, 0, 0]
						},
						"0.5": {
							"vector": [720, 0, 0]
						},
						"0.6": {
							"vector": [1080, 0, 0]
						},
						"0.7": {
							"vector": [1440, 0, 0]
						},
						"0.8": {
							"vector": [1980, 0, 0]
						},
						"1.1": {
							"vector": [2340, 0, 0]
						},
						"1.5": {
							"vector": [2700, 0, 0]
						},
						"2.0": {
							"vector": [2980, 0, 0]
						}
					}
				},
				"mid_complex_cogwheel": {
					"rotation": {
						"0.1": {
							"vector": [0, 0, 0]
						},
						"0.4": {
							"vector": [-480, 0, 0]
						},
						"0.6": {
							"vector": [-840, 0, 0]
						},
						"0.7": {
							"vector": [-1200, 0, 0]
						},
						"0.8": {
							"vector": [-1600, 0, 0]
						},
						"1.1": {
							"vector": [-1960, 0, 0]
						},
						"1.5": {
							"vector": [-2320, 0, 0]
						},
						"2.0": {
							"vector": [-2560, 0, 0]
						}
					}
				},
				"mini_complex_cogwheel": {
					"rotation": {
						"0.1": {
							"vector": [0, 0, 0]
						},
						"0.2": {
							"vector": [360, 0, 0]
						},
						"0.3": {
							"vector": [720, 0, 0]
						},
						"0.4": {
							"vector": [1080, 0, 0]
						},
						"0.5": {
							"vector": [1440, 0, 0]
						},
						"0.8": {
							"vector": [1800, 0, 0]
						},
						"1.2": {
							"vector": [2157.5, 0, 0]
						},
						"1.7": {
							"vector": [2517.5, 0, 0]
						},
						"2.2": {
							"vector": [2875, 0, 0]
						}
					}
				},
				"plate_1": {
					"position": {
						"0.0": {
							"vector": [0, 0, 0]
						},
						"0.0333": {
							"vector": [0.05, 0, 0]
						},
						"0.1": {
							"vector": [0.125, 0.05, 0]
						},
						"0.1667": {
							"vector": [0.125, 0.975, 0]
						},
						"0.2333": {
							"vector": [0.1, 2.675, 0]
						},
						"0.2667": {
							"vector": [0, 2.855, 0]
						},
						"0.3": {
							"vector": [0, 2.675, 0]
						},
						"0.5": {
							"vector": [0, 2.6, 0]
						},
						"1.5": {
							"vector": [0, 2.6, 0]
						},
						"1.9333": {
							"vector": [0.1, 2.675, 0]
						},
						"2.1667": {
							"vector": [0.125, 0.975, 0]
						},
						"2.2": {
							"vector": [0.125, 0.05, 0]
						},
						"2.2333": {
							"vector": [0.05, 0, 0]
						},
						"2.2667": {
							"vector": [0, 0, 0]
						},
						"2.3": {
							"vector": [0, 0, 0.075]
						},
						"2.3333": {
							"vector": [0, 0, 0]
						},
						"2.3667": {
							"vector": [0, 0, -0.05]
						},
						"2.4": {
							"vector": [0, 0, 0]
						}
					}
				},
				"plate_2": {
					"position": {
						"0.0": {
							"vector": [0, 0, 0]
						},
						"0.0333": {
							"vector": [0, 0, -0.05]
						},
						"0.1": {
							"vector": [0, 0, -0.1]
						},
						"0.1667": {
							"vector": [0, 0.475, -0.1]
						},
						"0.2333": {
							"vector": [0, 1.48, -0.075]
						},
						"0.2667": {
							"vector": [0, 1.6, 0]
						},
						"0.3": {
							"vector": [0, 1.45, 0]
						},
						"0.5": {
							"vector": [0, 1.3, 0]
						},
						"1.5": {
							"vector": [0, 1.3, 0]
						},
						"1.9333": {
							"vector": [0, 1.48, -0.075]
						},
						"2.1667": {
							"vector": [0, 0.475, -0.1]
						},
						"2.2": {
							"vector": [0, 0, -0.1]
						},
						"2.2333": {
							"vector": [0, 0, -0.05]
						},
						"2.2667": {
							"vector": [0, 0, 0]
						},
						"2.3": {
							"vector": [0.075, 0, 0]
						},
						"2.3333": {
							"vector": [0, 0, 0]
						},
						"2.3667": {
							"vector": [-0.05, 0, 0]
						},
						"2.4": {
							"vector": [0, 0, 0]
						}
					}
				},
				"plate_cogwheel_1": {
					"rotation": {
						"0.1333": {
							"vector": [0, 0, 0]
						},
						"0.3": {
							"vector": [-180, 0, 0]
						},
						"1.9333": {
							"vector": [-180, 0, 0]
						},
						"2.2": {
							"vector": [0, 0, 0]
						}
					}
				},
				"plate_cogwheel_2": {
					"rotation": {
						"0.1333": {
							"vector": [0, 0, 0]
						},
						"0.3": {
							"vector": [-180, 0, 0]
						},
						"1.9333": {
							"vector": [-180, 0, 0]
						},
						"2.2": {
							"vector": [0, 0, 0]
						}
					}
				},
				"rotation_fix": {
					"rotation": {
						"0.0": {
							"vector": [0, 0, 0]
						},
						"0.4333": {
							"vector": [0, 0, 7.5]
						},
						"0.4667": {
							"vector": [-2.5, 0, 7.5]
						},
						"2.6333": {
							"vector": [-2.5, 0, 7.5]
						},
						"3.7": {
							"vector": [-4.99838, -0.06525, 8.00523]
						},
						"5.3": {
							"vector": [-4.99838, -0.06525, 8.00523]
						},
						"6.0": {
							"vector": [0, 0, 0]
						}
					}
				}
			}
		},
		"animation.gauntlet.deploy": {
			"animation_length": 0.6,
			"override_previous_animation": true,
			"bones": {
				"root": {
					"position": {
						"0.0": {
							"vector": [0, 0, 0]
						},
						"0.3": {
							"vector": [-0.2, 0, 0.1]
						},
						"0.4": {
							"vector": [0, 0, 0]
						},
						"0.4333": {
							"vector": [-0.1, 0, -0.1]
						},
						"0.5": {
							"vector": [0, 0, -0.1]
						},
						"0.5333": {
							"vector": [0, 0, 0]
						}
					}
				},
				"needle": {
					"rotation": {
						"0.0": {
							"vector": [0, 0, 0]
						},
						"0.2667": {
							"vector": [-174, 0, 0]
						},
						"0.5333": {
							"vector": [-74, 0, 0]
						}
					}
				},
				"push": {
					"position": {
						"0.0": {
							"vector": [0, 0, 0]
						},
						"0.1333": {
							"vector": [0, -0.7, 0]
						},
						"0.1667": {
							"vector": [0, -1.9, 0]
						},
						"0.2": {
							"vector": [0, -2.5, 0]
						},
						"0.3333": {
							"vector": [0, -2.5, 0]
						},
						"0.5333": {
							"vector": [0, 0, 0]
						}
					}
				},
				"plate_1": {
					"position": {
						"0.0": {
							"vector": [0, 0, 0]
						},
						"0.1667": {
							"vector": [0.1, 0.2, 0]
						},
						"0.3": {
							"vector": [0.1, 0.3, 0]
						},
						"0.4667": {
							"vector": [0, 0.2, 0]
						},
						"0.6": {
							"vector": [0, 0, 0]
						}
					}
				},
				"plate_2": {
					"position": {
						"0.0": {
							"vector": [0, 0, 0]
						},
						"0.1667": {
							"vector": [0, 0.2, -0.1]
						},
						"0.3": {
							"vector": [0, 0.3, -0.1]
						},
						"0.4667": {
							"vector": [0, 0.2, 0]
						},
						"0.6": {
							"vector": [0, 0, 0]
						}
					}
				},
				"rotation_fix": {
					"rotation": {
						"0.0": {
							"vector": [-10.34912, 1.90205, 18.31157]
						},
						"0.1": {
							"vector": [5.1044, -0.222, -4.12104]
						},
						"0.2": {
							"vector": [11.92314, 1.10984, -7.92314]
						},
						"0.3667": {
							"vector": [5.23631, 0.9526, -8.50066]
						},
						"0.4667": {
							"vector": [0.13882, 0.47069, -1.75025]
						},
						"0.5667": {
							"vector": [0, 0, 0]
						}
					},
					"position": {
						"0.0": {
							"vector": [0, -0.4, 0]
						},
						"0.3": {
							"vector": [0, 0.2, 0]
						},
						"0.4667": {
							"vector": [-0.1, 0.1, 0]
						},
						"0.5": [-0.09458, 0.09458, 0],
						"0.5667": [-0.00542, 0.00542, 0],
						"0.6": {
							"vector": [0, 0, 0]
						}
					}
				}
			}
		}
	},
	"geckolib_format_version": 2
}